{"annotation": {"filename": "4.jpg", "folder": "users/nh2722//3dimages", "source": {"submittedBy": "Nahyun Kwon"}, "imagesize": {"nrows": null, "ncols": null}, "object": [{"name": "support", "deleted": "0", "verified": "0", "occluded": "no", "attributes": null, "parts": {"hasparts": null, "ispartof": null}, "date": "02-10-20 16:55:42:177", "id": "0", "type": "bounding_box", "polygon": {"username": "nh2722", "pt": [{"x": "47", "y": "95", "time": "02-10-20 16:55:39:375"}, {"x": "125", "y": "95", "time": "02-10-20 16:55:40:665"}, {"x": "125", "y": "153", "time": "undefined"}, {"x": "47", "y": "153", "time": "undefined"}], "closed_date": "02-10-20 16:55:40:665"}}, {"name": "support", "deleted": "0", "verified": "0", "occluded": "no", "attributes": null, "parts": {"hasparts": null, "ispartof": null}, "date": "02-10-20 16:55:52:605", "id": "1", "type": "bounding_box", "polygon": {"username": "nh2722", "pt": [{"x": "226", "y": "106", "time": "02-10-20 16:55:51:017"}, {"x": "289", "y": "106", "time": "02-10-20 16:55:51:668"}, {"x": "289", "y": "190", "time": "undefined"}, {"x": "226", "y": "190", "time": "undefined"}], "closed_date": "02-10-20 16:55:51:669"}}, {"name": "support", "deleted": "0", "verified": "0", "occluded": "no", "attributes": null, "parts": {"hasparts": null, "ispartof": null}, "date": "02-10-20 16:55:55:102", "id": "2", "type": "bounding_box", "polygon": {"username": "nh2722", "pt": [{"x": "494", "y": "114", "time": "02-10-20 16:55:53:619"}, {"x": "554", "y": "114", "time": "02-10-20 16:55:54:312"}, {"x": "554", "y": "201", "time": "undefined"}, {"x": "494", "y": "201", "time": "undefined"}], "closed_date": "02-10-20 16:55:54:313"}}]}}